lemon8/__main__.py
lemon8/bin/FONT
lemon8/bin/ibm.ch8
lemon8/components/__init__.py
lemon8/components/constants.py
lemon8/components/cpu.py
lemon8/components/display.py
lemon8/components/keypad.py
lemon8/components/memory.py
lemon8/components/opcode.py
lemon8/static/beep.mp3
lemon8/static/play.png
lemon8-1.3.14.dist-info/LICENSE
lemon8-1.3.14.dist-info/WHEEL
lemon8-1.3.14.dist-info/METADATA
lemon8-1.3.14.dist-info/RECORD
